authentication_factory/.version
authentication_factory/__init__.py
authentication_factory/auth_decorators.py
authentication_factory/auth_factory.py
authentication_factory/auth/__init__.py
authentication_factory/auth/ms_oauth2.py
authentication_factory-0.0.5.dist-info/LICENSE
authentication_factory-0.0.5.dist-info/METADATA
authentication_factory-0.0.5.dist-info/WHEEL
authentication_factory-0.0.5.dist-info/top_level.txt
authentication_factory-0.0.5.dist-info/RECORD
