Metadata-Version: 2.1
Name: authentication-factory
Version: 0.0.5
Summary: Implementation for Microsoft Oauth2 authentication
Home-page: https://github.com/shrivastava-v-ankit/authentication-factory
Author: Ankit Shrivastava
License: MIT
Project-URL: Source, https://github.com/shrivastava-v-ankit/authentication-factory/
Project-URL: Tracker, https://github.com/shrivastava-v-ankit/authentication-factory/issues
Keywords: streamlit,flask,microsoft,json web token,oauth2,authentication
Platform: any
Classifier: Development Status :: 5 - Production/Stable
Classifier: Environment :: Web Environment
Classifier: Framework :: Flask
Classifier: Intended Audience :: Developers
Classifier: Natural Language :: English
Classifier: License :: OSI Approved :: MIT License
Classifier: Operating System :: OS Independent
Classifier: Programming Language :: Python :: 3.9
Classifier: Programming Language :: Python :: 3.10
Classifier: Programming Language :: Python :: 3.11
Classifier: Programming Language :: Python :: 3.12
Classifier: Topic :: Software Development :: Libraries :: Python Modules
Classifier: Topic :: Software Development :: Version Control :: Git
Requires-Python: >=3.9, <=3.12.4
License-File: LICENSE
Requires-Dist: PyJWT <=2.8.0
Requires-Dist: certifi <=2024.7.4
Requires-Dist: cffi <=1.16.0
Requires-Dist: charset-normalizer <=3.3.2
Requires-Dist: cryptography <=42.0.8
Requires-Dist: idna <=3.7
Requires-Dist: msal <=1.29.0
Requires-Dist: pycparser <=2.22
Requires-Dist: pyopenssl <=24.1.0
Requires-Dist: requests <=2.32.3
Requires-Dist: urllib3 <=2.2.2
